{"date": "2026-06-10", "total": 7907, "rare": 0, "squawk": 2, "filtered": 1346, "types": {"ZZZZ": 85, "A310": 48, "AN12": 133, "B779": 13, "B742": 140, "B732": 27, "B733": 1330, "B734": 1881, "B735": 662, "B736": 81, "DC10": 33, "DC91": 13, "F100": 170, "F5": 14, "IL76": 301, "MD82": 63, "MD83": 269, "MD87": 16, "MD88": 91, "V22": 246, "T204": 367, "SHIP": 137, "BTB2": 253, "F70": 362, "D328": 141, "YK42": 34, "DC3": 88, "L410": 317, "L188": 9, "F16": 17, "F28": 1, "DC6": 25, "AN32": 153, "B52": 11, "A148": 122, "BALL": 80, "T154": 24, "T134": 31, "AN26": 43, "F27": 3, "AN30": 27, "DC87": 1, "YK40": 10, "A124": 22, "AN72": 1, "B722": 3, "F35": 3, "P3": 2, "IL62": 4}}