{"date": "2026-04-13", "total": 6326, "rare": 0, "squawk": 0, "filtered": 1110, "types": {"ZZZZ": 153, "A124": 153, "A148": 41, "AN72": 16, "B742": 118, "B733": 1026, "B734": 1205, "B735": 360, "B736": 197, "DC3": 60, "BALL": 128, "F100": 108, "IL76": 435, "L410": 553, "MD82": 31, "MD83": 99, "MD88": 110, "P3": 17, "YK42": 61, "V22": 56, "BTB2": 225, "F70": 367, "B732": 41, "MD81": 12, "D328": 55, "B722": 111, "F16": 8, "T204": 154, "AN32": 167, "AN12": 73, "AN26": 77, "IL62": 7, "T134": 7, "A310": 29, "YK40": 3, "T154": 8, "F35": 1, "CORS": 6, "B703": 12, "F5": 31, "T38": 5}}