{"date": "2026-06-25", "total": 918, "rare": 0, "squawk": 0, "filtered": 124, "types": {"L188": 16, "ZZZZ": 11, "B52": 11, "A124": 12, "A148": 9, "A310": 6, "AN32": 7, "B732": 5, "B733": 183, "B734": 172, "B735": 54, "B736": 23, "DC3": 2, "DC10": 11, "BALL": 22, "F100": 9, "IL76": 31, "L410": 14, "MD11": 1, "MD83": 15, "MD87": 30, "MD88": 21, "YK42": 22, "V22": 45, "U2": 10, "T204": 35, "SHIP": 11, "BTB2": 11, "F70": 51, "D328": 34, "B742": 10, "E6": 3, "L101": 7, "T134": 6, "AN12": 5, "MD82": 3}}