{"date": "2026-06-12", "total": 6864, "rare": 0, "squawk": 2, "filtered": 1166, "types": {"A310": 144, "AN12": 91, "AN26": 33, "B732": 29, "B733": 1272, "B734": 2003, "B735": 375, "B736": 36, "DC10": 77, "BALL": 27, "F5": 10, "MD81": 6, "MD82": 53, "MD83": 157, "MD87": 30, "MD88": 180, "P3": 22, "V22": 244, "T204": 175, "SHIP": 96, "BTB2": 426, "D328": 88, "B742": 90, "L410": 265, "DC6": 3, "ZZZZ": 51, "F100": 94, "T134": 7, "IL76": 229, "F70": 197, "AN32": 118, "L188": 4, "DC3": 59, "IL62": 37, "A124": 36, "T154": 30, "A148": 26, "F35": 2, "F27": 6, "YK40": 15, "RFAL": 10, "DC87": 11}}