{"date": "2026-04-09", "total": 14593, "rare": 9, "squawk": 0, "filtered": 1878, "types": {"ZZZZ": 438, "A124": 232, "AN12": 152, "AN32": 196, "AN72": 33, "B779": 41, "B732": 319, "B703": 37, "B733": 2795, "B734": 3649, "B735": 480, "B736": 291, "DC3": 291, "F100": 185, "F5": 243, "IL76": 385, "L410": 466, "MD83": 372, "MD87": 40, "MD88": 122, "P3": 151, "V22": 730, "T204": 342, "BTB2": 107, "E6": 22, "F70": 435, "D328": 393, "WB57": 9, "GLF3": 10, "BALL": 344, "MD82": 98, "DC6": 26, "B722": 98, "MD81": 33, "T134": 24, "GLF5": 7, "F16": 62, "SHIP": 148, "AN26": 84, "B742": 137, "YK42": 41, "T154": 65, "YK40": 4, "A148": 71, "IL62": 11, "F15": 17, "A3ST": 35, "DC87": 33, "BER2": 18, "KFIR": 34, "T38": 71, "A310": 83, "L188": 29, "B52": 26, "T34T": 4, "EC35": 9, "DC91": 4, "MD11": 10, "YK50": 1}}