{"date": "2026-04-18", "total": 9389, "rare": 0, "squawk": 0, "filtered": 1525, "types": {"ZZZZ": 392, "A124": 148, "B732": 158, "B733": 1670, "B734": 2029, "B735": 388, "B736": 145, "DC3": 177, "BALL": 850, "F100": 119, "IL76": 297, "MD81": 20, "MD83": 157, "MD88": 43, "V22": 140, "T204": 410, "SHIP": 259, "F70": 222, "D328": 236, "MD87": 47, "BTB2": 9, "MD82": 93, "B742": 116, "L410": 317, "AN12": 158, "IL62": 14, "E6": 3, "B703": 43, "A310": 212, "B74S": 83, "DC6": 16, "AN32": 143, "P3": 11, "T154": 73, "AN72": 6, "BER2": 25, "AN26": 20, "T134": 9, "A148": 24, "YK40": 12, "YK50": 1, "YK42": 51, "U2": 28, "L188": 3, "DC10": 10, "CORS": 2}}