{"date": "2026-04-17", "total": 10833, "rare": 22, "squawk": 0, "filtered": 1730, "types": {"ZZZZ": 328, "A124": 147, "A310": 170, "AN32": 211, "B742": 207, "B732": 219, "B703": 35, "B733": 1796, "B734": 2640, "B735": 412, "B736": 233, "DC6": 40, "DC3": 112, "BALL": 409, "F100": 90, "F5": 195, "IL76": 407, "MD82": 105, "MD83": 140, "P3": 71, "V22": 492, "T204": 229, "SHIP": 289, "BTB2": 138, "F70": 280, "D328": 264, "WB57": 22, "T38": 55, "MD87": 17, "L188": 8, "B722": 27, "F28": 2, "L410": 520, "IL62": 51, "YK42": 84, "MD88": 52, "T154": 84, "AN12": 20, "AN26": 117, "A148": 11, "CORS": 3, "AN72": 6, "T134": 1, "F104": 7, "U2": 25, "YK50": 3, "KFIR": 7, "GLF3": 26, "DC10": 10, "F16": 9, "B779": 6, "MD81": 1}}