{"date": "2026-06-03", "total": 8885, "rare": 0, "squawk": 0, "filtered": 1478, "types": {"A310": 127, "AN12": 187, "B732": 99, "B733": 1303, "B734": 2352, "B735": 626, "B736": 116, "DC6": 6, "DC3": 96, "F100": 194, "F5": 6, "IL76": 226, "MD82": 124, "MD83": 305, "MD87": 39, "MD88": 120, "V22": 428, "T204": 328, "SHIP": 109, "BTB2": 295, "F70": 403, "D328": 151, "AN26": 106, "DC10": 72, "T154": 38, "A148": 52, "DC91": 30, "BALL": 42, "ZZZZ": 103, "L410": 364, "T134": 28, "AN32": 157, "YK42": 13, "AN30": 32, "B742": 121, "P3": 22, "BER2": 2, "B741": 5, "YK40": 9, "MD81": 13, "F28": 8, "F35": 2, "BE20": 7, "GLF5": 6, "SGUP": 4, "A124": 4, "GLF3": 3, "B1": 1, "F16": 1}}