{"date": "2026-07-01", "total": 3826, "rare": 0, "squawk": 0, "filtered": 501, "types": {"ZZZZ": 40, "A310": 72, "AN26": 34, "B732": 10, "B733": 740, "B734": 828, "B735": 325, "B736": 38, "DC6": 1, "DC3": 36, "BALL": 174, "F100": 111, "F5": 11, "IL76": 117, "L410": 203, "MD11": 18, "MD83": 62, "MD87": 13, "MD88": 68, "P3": 4, "V22": 113, "T204": 109, "T154": 4, "SHIP": 57, "BTB2": 115, "F70": 149, "D328": 67, "T38": 5, "DC10": 12, "IL62": 25, "AN12": 49, "T134": 12, "AN32": 58, "B742": 43, "A124": 25, "MD82": 29, "A148": 14, "AN30": 3, "YK40": 6, "BER2": 15, "AN72": 4, "A3ST": 7}}