{"date": "2026-06-21", "total": 10742, "rare": 0, "squawk": 0, "filtered": 1726, "types": {"A310": 264, "B732": 166, "B722": 35, "B733": 2174, "B734": 2373, "B735": 916, "DC10": 34, "BALL": 727, "F100": 182, "L410": 284, "MD83": 288, "MD87": 174, "MD88": 88, "P3": 5, "V22": 167, "T204": 382, "SHIP": 378, "BTB2": 183, "MD82": 171, "ZZZZ": 205, "T134": 52, "IL76": 296, "T154": 25, "F70": 183, "DC3": 172, "D328": 183, "AN12": 79, "YK42": 94, "A148": 34, "AN30": 35, "B742": 96, "DC87": 2, "AN26": 32, "L188": 18, "CORS": 28, "AN32": 2, "B736": 59, "A124": 43, "F5": 6, "B741": 7, "YK40": 32, "AN72": 18, "MD81": 15, "E6": 20, "B779": 11, "MD11": 4}}