{"date": "2026-06-08", "total": 10061, "rare": 16, "squawk": 0, "filtered": 2014, "types": {"AN32": 179, "B733": 1424, "B734": 2028, "B735": 537, "DC3": 166, "DC10": 40, "IL76": 442, "L410": 584, "MD81": 21, "MD87": 37, "MD88": 32, "V22": 285, "T204": 373, "T134": 14, "SHIP": 264, "BTB2": 419, "F70": 389, "D328": 307, "AN26": 92, "B722": 144, "B736": 94, "MD83": 303, "T38": 40, "F100": 81, "MD82": 154, "AN12": 155, "ZZZZ": 205, "T154": 90, "BALL": 78, "B742": 81, "AN30": 41, "YK42": 38, "DC6": 28, "A148": 62, "A124": 44, "AN72": 12, "IL62": 3, "YK40": 6, "DC87": 28, "P3": 128, "B732": 192, "F5": 154, "GLF3": 37, "B703": 25, "KFIR": 6, "B52": 91, "F16": 18, "A310": 33, "F15": 4, "B1": 4, "WB57": 16, "GLF5": 16, "CORS": 14, "T34T": 3}}