{"date": "2026-05-29", "total": 2240, "rare": 0, "squawk": 0, "filtered": 355, "types": {"ZZZZ": 19, "AN26": 20, "AN32": 50, "B733": 437, "B734": 584, "B735": 102, "B736": 54, "DC3": 29, "DC10": 60, "F16": 3, "F5": 23, "IL76": 85, "MD82": 24, "MD83": 75, "MD87": 17, "V22": 157, "T204": 42, "SHIP": 62, "F70": 89, "D328": 44, "EC35": 27, "L188": 3, "B732": 31, "B742": 28, "IL62": 26, "F100": 12, "L410": 53, "T154": 2, "DC91": 13, "DC6": 7, "MD88": 17, "BALL": 33, "P3": 3, "AN30": 2, "BTB2": 5, "YK42": 1, "A124": 1}}