{"date": "2026-04-22", "total": 13829, "rare": 21, "squawk": 3, "filtered": 2063, "types": {"A310": 153, "B742": 98, "B732": 315, "B733": 2026, "B734": 3204, "B735": 642, "B736": 241, "DC3": 227, "DC91": 28, "BALL": 447, "F16": 61, "F100": 144, "F5": 218, "IL76": 638, "MD83": 213, "P3": 55, "V22": 787, "T204": 287, "SHIP": 211, "BTB2": 241, "F70": 504, "D328": 250, "ZZZZ": 407, "MD87": 99, "AN32": 296, "DC6": 63, "MD82": 157, "MD88": 84, "L410": 516, "AN12": 255, "T154": 103, "AN30": 43, "BER2": 7, "AN26": 149, "A148": 127, "F15": 5, "A3ST": 35, "DC87": 29, "AN72": 24, "B722": 30, "T134": 2, "A124": 115, "CORS": 2, "EC35": 11, "WB57": 21, "T38": 56, "YK50": 6, "U2": 4, "B772": 35, "L188": 8, "B52": 20, "KFIR": 32, "T34T": 10, "YK42": 11, "B779": 37, "DC10": 6, "MD81": 15, "B741": 1, "B703": 18}}