{"date": "2026-06-27", "total": 2344, "rare": 0, "squawk": 0, "filtered": 346, "types": {"L188": 34, "A148": 28, "B742": 35, "B733": 411, "B734": 541, "B735": 109, "DC3": 25, "DC91": 14, "BALL": 287, "F5": 6, "IL76": 107, "L410": 55, "MD83": 92, "MD87": 10, "YK42": 9, "V22": 108, "T204": 65, "SHIP": 37, "BTB2": 82, "D328": 17, "GLF5": 3, "ZZZZ": 31, "B736": 13, "CORS": 2, "F70": 30, "DC6": 1, "F100": 25, "A310": 60, "MD88": 13, "AN32": 37, "T134": 10, "AN12": 17, "A124": 23, "MD82": 6, "AN26": 1}}