{"date": "2026-04-23", "total": 5889, "rare": 0, "squawk": 0, "filtered": 1193, "types": {"ZZZZ": 64, "A124": 95, "A310": 69, "B703": 34, "B733": 917, "B734": 1437, "B735": 312, "B736": 80, "DC6": 8, "DC3": 42, "BALL": 245, "F100": 141, "IL76": 222, "L410": 303, "MD82": 41, "MD83": 105, "MD87": 32, "MD88": 55, "P3": 14, "V22": 274, "T204": 143, "SHIP": 182, "F70": 338, "D328": 115, "B732": 13, "F16": 37, "F35": 8, "T38": 6, "L188": 11, "AN32": 159, "AN12": 75, "B742": 63, "GLF3": 7, "IL62": 23, "B722": 32, "AN30": 21, "T134": 19, "YK42": 21, "BTB2": 11, "AN26": 79, "F27": 3, "A148": 13, "DC87": 5, "A3ST": 9, "BER2": 4, "DC91": 2}}