{"date": "2026-06-23", "total": 10027, "rare": 0, "squawk": 0, "filtered": 1350, "types": {"L188": 3, "A310": 169, "AN32": 21, "B732": 144, "B733": 1956, "B734": 2650, "B735": 848, "B736": 87, "DC3": 162, "BALL": 378, "F100": 153, "L410": 420, "MD83": 218, "MD87": 106, "MD88": 190, "V22": 122, "U2": 16, "T204": 248, "SHIP": 241, "BTB2": 155, "F70": 477, "D328": 195, "DC10": 17, "ZZZZ": 110, "IL76": 260, "MD82": 58, "DC6": 5, "AN12": 70, "A148": 35, "P3": 66, "IL62": 28, "AN26": 59, "B742": 85, "YK42": 21, "F35": 6, "A124": 31, "A3ST": 6, "B722": 28, "YK40": 1, "T154": 36, "MD81": 5, "MD11": 24, "F5": 29, "GLF5": 20, "F16": 13, "EC35": 14, "T38": 18, "KFIR": 12, "BE20": 10, "T134": 1}}