{"date": "2026-06-04", "total": 5567, "rare": 0, "squawk": 1, "filtered": 1025, "types": {"ZZZZ": 69, "A310": 104, "B732": 8, "B722": 42, "B733": 1061, "B734": 1336, "B735": 260, "B736": 46, "DC6": 6, "DC3": 50, "DC10": 26, "DC91": 110, "F100": 121, "F5": 12, "IL76": 190, "MD83": 212, "MD87": 1, "MD88": 99, "P3": 12, "V22": 232, "T204": 48, "BTB2": 318, "F70": 381, "D328": 82, "GLF5": 5, "A124": 41, "A148": 30, "AN12": 63, "MD82": 66, "T154": 23, "L410": 197, "AN32": 119, "IL62": 9, "YK42": 42, "T134": 11, "BALL": 59, "AN26": 24, "F35": 1, "DC87": 3, "B742": 16, "SHIP": 26, "AN72": 2, "YK40": 4}}