{"date": "2026-04-14", "total": 12034, "rare": 0, "squawk": 0, "filtered": 1855, "types": {"ZZZZ": 239, "A148": 148, "AN12": 144, "B742": 192, "B733": 2036, "B734": 3039, "B735": 563, "B736": 244, "DC6": 32, "BALL": 337, "F100": 163, "L410": 636, "MD83": 211, "MD87": 28, "MD88": 41, "P3": 152, "V22": 397, "T204": 277, "E6": 41, "F70": 413, "D328": 201, "A124": 281, "DC3": 171, "MD82": 115, "T38": 52, "SHIP": 47, "IL62": 105, "DC91": 21, "F16": 57, "B732": 163, "AN32": 47, "B722": 74, "AN26": 120, "IL76": 413, "YK42": 37, "YK40": 24, "A310": 152, "T154": 46, "BTB2": 42, "T134": 18, "CORS": 9, "DC87": 28, "EC35": 39, "A3ST": 30, "F5": 161, "B779": 24, "WHK2": 9, "L188": 17, "MD81": 13, "B703": 36, "B74S": 38, "B52": 52, "F35": 1, "T34T": 11, "KFIR": 13, "DC10": 17, "L101": 15, "MD11": 2}}