{"date": "2026-06-04", "total": 3386, "rare": 0, "squawk": 1, "filtered": 704, "types": {"ZZZZ": 66, "A310": 57, "B732": 8, "B722": 23, "B733": 642, "B734": 898, "B735": 116, "B736": 46, "DC6": 6, "DC3": 40, "DC10": 26, "DC91": 87, "F100": 64, "F5": 12, "IL76": 106, "MD83": 151, "MD87": 1, "MD88": 59, "P3": 6, "V22": 158, "T204": 26, "BTB2": 162, "F70": 214, "D328": 56, "GLF5": 5, "A124": 37, "A148": 14, "AN12": 39, "MD82": 47, "T154": 10, "L410": 63, "AN32": 58, "IL62": 9, "YK42": 25, "T134": 6, "BALL": 37, "AN26": 5, "F35": 1}}