{"date": "2026-06-25", "total": 8740, "rare": 0, "squawk": 2, "filtered": 1133, "types": {"L188": 57, "ZZZZ": 91, "B52": 16, "A124": 65, "A148": 49, "A310": 163, "AN32": 134, "B732": 48, "B733": 1598, "B734": 1993, "B735": 662, "B736": 107, "DC3": 41, "DC10": 25, "BALL": 275, "F100": 160, "IL76": 188, "L410": 404, "MD11": 3, "MD83": 110, "MD87": 104, "MD88": 173, "YK42": 77, "V22": 437, "U2": 18, "T204": 340, "SHIP": 180, "BTB2": 183, "F70": 348, "D328": 164, "B742": 90, "E6": 18, "L101": 10, "T134": 52, "AN12": 101, "MD82": 10, "F2TH": 2, "T154": 35, "F16": 14, "B722": 29, "AN26": 64, "IL62": 6, "YK40": 22, "A3ST": 22, "RFAL": 18, "AN72": 8, "DC87": 4, "F5": 14, "P3": 5, "T38": 3}}