{"date": "2026-06-30", "total": 3163, "rare": 0, "squawk": 0, "filtered": 528, "types": {"ZZZZ": 36, "A124": 61, "AN26": 30, "B779": 4, "B732": 10, "B733": 546, "B734": 624, "B735": 200, "B736": 18, "DC3": 4, "BALL": 171, "F16": 1, "F100": 58, "IL76": 148, "L410": 109, "MD82": 24, "MD83": 57, "MD87": 47, "MD88": 27, "P3": 6, "V22": 117, "T204": 92, "SHIP": 67, "BTB2": 149, "F70": 159, "D328": 50, "F5": 25, "AN12": 38, "DC6": 1, "T154": 17, "B742": 59, "DC91": 38, "MD11": 9, "AN32": 58, "A310": 58, "T134": 3, "DC10": 5, "A148": 11, "YK40": 6, "IL62": 7, "BER2": 1, "AN72": 3, "DC87": 6, "YK42": 3}}