{"date": "2026-05-18", "total": 4256, "rare": 0, "squawk": 0, "filtered": 803, "types": {"A124": 51, "A310": 58, "B742": 52, "B722": 43, "B733": 862, "B734": 673, "B735": 336, "DC3": 67, "DC10": 16, "BALL": 91, "IL62": 6, "IL76": 251, "MD82": 9, "MD83": 52, "MD87": 79, "MD88": 123, "T204": 105, "SHIP": 75, "E6": 52, "F70": 210, "D328": 51, "T38": 12, "AN32": 132, "F100": 137, "ZZZZ": 19, "MD81": 4, "B736": 25, "V22": 89, "AN12": 42, "L410": 266, "BTB2": 162, "DC91": 18, "CORS": 1, "P3": 8, "T134": 11, "AN26": 26, "B741": 6, "A148": 30, "A3ST": 1, "YK40": 5}}