{"date": "2026-06-23", "total": 7244, "rare": 0, "squawk": 0, "filtered": 1046, "types": {"L188": 3, "A310": 135, "AN32": 5, "B732": 45, "B733": 1464, "B734": 1851, "B735": 660, "B736": 46, "DC3": 91, "BALL": 287, "F100": 132, "L410": 290, "MD83": 144, "MD87": 102, "MD88": 155, "V22": 109, "U2": 16, "T204": 216, "SHIP": 177, "BTB2": 126, "F70": 443, "D328": 105, "DC10": 17, "ZZZZ": 79, "IL76": 180, "MD82": 32, "DC6": 5, "AN12": 70, "A148": 31, "P3": 27, "IL62": 28, "AN26": 47, "B742": 66, "YK42": 11, "F35": 6, "A124": 18, "A3ST": 6, "B722": 3, "YK40": 1, "T154": 10, "MD81": 5}}