{"date": "2026-04-24", "total": 1378, "rare": 0, "squawk": 0, "filtered": 187, "types": {"ZZZZ": 14, "A124": 19, "A310": 2, "AN12": 17, "B779": 12, "B732": 18, "B703": 6, "B733": 219, "B734": 386, "B735": 71, "B736": 46, "DC6": 10, "BALL": 55, "IL62": 7, "IL76": 25, "L410": 37, "MD83": 22, "MD88": 26, "V22": 73, "T204": 21, "SHIP": 30, "BTB2": 57, "E6": 13, "D328": 27, "MD82": 9, "MD87": 16, "T154": 11, "DC3": 20, "F100": 6, "F16": 19, "T38": 20, "P3": 12, "L188": 4, "YK50": 12, "F70": 23, "F5": 1, "T134": 4, "AN32": 8}}