{"date": "2026-06-01", "total": 9967, "rare": 0, "squawk": 0, "filtered": 1574, "types": {"A124": 56, "AN12": 140, "B732": 237, "B733": 1615, "B734": 1969, "B735": 680, "B736": 130, "DC3": 156, "DC91": 48, "IL76": 393, "L410": 562, "MD82": 123, "MD83": 236, "V22": 234, "T204": 363, "T134": 33, "SHIP": 318, "BTB2": 311, "F70": 348, "DC10": 27, "P3": 84, "F100": 187, "MD88": 118, "MD81": 8, "ZZZZ": 189, "B722": 69, "T154": 2, "AN32": 224, "BER2": 22, "A148": 80, "B742": 85, "BALL": 141, "L188": 1, "AN26": 80, "AN30": 39, "A310": 115, "D328": 217, "AN72": 4, "YK40": 6, "F28": 19, "MD87": 25, "F5": 93, "IL62": 28, "B52": 55, "GLF3": 29, "F16": 32, "U2": 25, "EC35": 7, "DC6": 2, "YK42": 2}}