{"date": "2026-04-09", "total": 12873, "rare": 9, "squawk": 0, "filtered": 1730, "types": {"ZZZZ": 384, "A124": 189, "AN12": 152, "AN32": 196, "AN72": 26, "B779": 34, "B732": 261, "B703": 20, "B733": 2424, "B734": 3263, "B735": 431, "B736": 234, "DC3": 257, "F100": 161, "F5": 203, "IL76": 381, "L410": 461, "MD83": 312, "MD87": 35, "MD88": 71, "P3": 151, "V22": 582, "T204": 298, "BTB2": 77, "E6": 18, "F70": 421, "D328": 344, "WB57": 9, "GLF3": 10, "BALL": 320, "MD82": 75, "DC6": 20, "B722": 98, "MD81": 33, "T134": 24, "GLF5": 7, "F16": 35, "SHIP": 126, "AN26": 75, "B742": 124, "YK42": 36, "T154": 65, "YK40": 4, "A148": 71, "IL62": 11, "F15": 17, "A3ST": 35, "DC87": 33, "BER2": 18, "KFIR": 34, "T38": 62, "A310": 64, "L188": 29, "B52": 26, "T34T": 4, "EC35": 9, "DC91": 4, "MD11": 8, "YK50": 1}}