{"date": "2026-05-27", "total": 5084, "rare": 0, "squawk": 0, "filtered": 811, "types": {"L188": 6, "A124": 43, "A310": 88, "AN32": 136, "B742": 31, "B732": 12, "B733": 751, "B734": 1245, "B735": 372, "B736": 85, "DC10": 77, "BALL": 86, "F16": 16, "F100": 124, "IL76": 206, "MD83": 190, "P3": 12, "V22": 179, "T204": 145, "SHIP": 96, "BTB2": 281, "F70": 280, "D328": 25, "MD87": 2, "T154": 4, "E6": 11, "B703": 39, "L410": 195, "MD82": 12, "DC6": 1, "YK42": 43, "AN12": 63, "MD88": 63, "DC3": 18, "F28": 1, "ZZZZ": 53, "T134": 17, "A148": 24, "AN26": 2, "B1": 19, "A3ST": 12, "AN30": 4, "B722": 14, "AN72": 1}}