{"date": "2026-04-21", "total": 5390, "rare": 29, "squawk": 0, "filtered": 1049, "types": {"ZZZZ": 60, "A124": 63, "A310": 67, "B742": 60, "B732": 16, "B703": 36, "B733": 696, "B734": 1245, "B735": 275, "B736": 74, "DC3": 43, "BALL": 176, "IL76": 311, "MD83": 79, "MD87": 23, "MD88": 36, "P3": 19, "V22": 183, "T204": 212, "SHIP": 122, "BTB2": 182, "E6": 21, "F70": 302, "D328": 107, "BE20": 2, "GLF3": 4, "DC91": 62, "MD82": 15, "MD81": 4, "F100": 93, "EC35": 11, "L410": 321, "T38": 48, "AN32": 192, "IL62": 12, "AN12": 44, "T134": 18, "T154": 14, "A148": 16, "F16": 24, "YK42": 16, "AN26": 51, "WB57": 29, "A3ST": 6}}