{"date": "2026-06-06", "total": 2029, "rare": 0, "squawk": 0, "filtered": 345, "types": {"L188": 24, "B52": 4, "A124": 27, "A148": 13, "A310": 20, "B733": 350, "B734": 602, "B735": 126, "DC6": 5, "DC3": 52, "F5": 16, "IL76": 69, "MD82": 65, "MD83": 62, "MD87": 53, "V22": 62, "T204": 94, "T154": 3, "SHIP": 32, "BTB2": 128, "F70": 27, "D328": 11, "T134": 14, "B732": 2, "B1": 8, "B736": 20, "F28": 1, "L410": 26, "F100": 9, "ZZZZ": 8, "B742": 8, "AN12": 25, "DC10": 16, "AN32": 11, "BALL": 17, "MD88": 19}}