{"date": "2026-05-20", "total": 9663, "rare": 0, "squawk": 0, "filtered": 1490, "types": {"A124": 62, "AN12": 38, "B733": 1781, "B734": 2503, "B735": 674, "B736": 180, "DC3": 154, "DC10": 28, "F100": 179, "IL76": 414, "L410": 413, "MD83": 263, "MD87": 88, "MD88": 165, "P3": 35, "V22": 529, "T204": 205, "SHIP": 170, "F70": 362, "D328": 182, "MD82": 124, "BTB2": 30, "T154": 27, "B732": 113, "DC6": 6, "ZZZZ": 98, "BER2": 31, "AN32": 250, "B722": 28, "A148": 61, "B742": 75, "BALL": 22, "A310": 118, "YK42": 8, "AN26": 44, "T134": 17, "IL62": 40, "AN30": 19, "DC91": 40, "A3ST": 30, "MD81": 6, "F15": 10, "AN72": 13, "F28": 3, "F5": 5, "EC35": 13, "B1": 6, "B52": 1}}