{"date": "2026-05-16", "total": 9037, "rare": 0, "squawk": 0, "filtered": 1497, "types": {"A124": 163, "A148": 39, "A310": 74, "B742": 191, "B732": 75, "B722": 54, "B733": 1499, "B734": 2275, "B735": 399, "B736": 98, "DC6": 14, "DC3": 148, "BALL": 363, "IL76": 402, "MD83": 430, "MD87": 85, "MD88": 26, "P3": 16, "V22": 99, "T204": 355, "SHIP": 274, "BTB2": 151, "E6": 31, "D328": 219, "ZZZZ": 176, "DC10": 3, "F100": 193, "MD82": 87, "F5": 6, "L410": 304, "F70": 186, "AN26": 54, "CORS": 6, "AN32": 193, "AN12": 95, "T154": 9, "YK42": 33, "AN72": 6, "YK50": 1, "YK40": 8, "MD81": 26, "DC91": 34, "L188": 21, "U2": 38, "KFIR": 17, "T2": 6, "B703": 28, "GLF3": 25, "F28": 2}}