{"date": "2026-06-02", "total": 6018, "rare": 0, "squawk": 12, "filtered": 1058, "types": {"L188": 33, "ZZZZ": 54, "A124": 81, "A310": 100, "B732": 60, "B733": 823, "B734": 1362, "B735": 329, "DC3": 70, "DC10": 52, "F100": 126, "F5": 36, "IL62": 14, "IL76": 139, "L410": 236, "MD81": 1, "MD83": 318, "MD88": 181, "P3": 26, "YK42": 13, "V22": 125, "T204": 212, "SHIP": 131, "BTB2": 338, "F70": 356, "D328": 97, "DC6": 10, "AN32": 262, "B736": 44, "MD82": 25, "B742": 98, "B722": 44, "AN12": 84, "B703": 13, "DC91": 30, "BALL": 31, "AN26": 27, "T134": 8, "YK40": 14, "T154": 13, "AN72": 2}}