{"date": "2026-05-17", "total": 6312, "rare": 0, "squawk": 0, "filtered": 1107, "types": {"L188": 2, "ZZZZ": 187, "A124": 81, "A310": 98, "AN12": 87, "B732": 123, "B733": 1260, "B734": 1414, "B735": 514, "DC3": 82, "MD83": 147, "MD87": 40, "MD88": 43, "P3": 10, "T204": 172, "SHIP": 227, "E6": 14, "B736": 51, "MD82": 109, "F100": 174, "IL76": 192, "F70": 193, "L410": 172, "DC6": 7, "B742": 127, "YK42": 33, "BALL": 293, "B722": 27, "T154": 35, "CORS": 4, "BTB2": 39, "DC87": 3, "AN26": 19, "V22": 17, "D328": 198, "A148": 61, "AN32": 26, "B741": 6, "F28": 8, "F27": 3, "B703": 7, "IL62": 4, "F5": 3}}