{"date": "2026-05-11", "total": 3279, "rare": 0, "squawk": 0, "filtered": 555, "types": {"ZZZZ": 104, "A124": 23, "A310": 59, "AN12": 13, "AN26": 49, "B732": 178, "B733": 507, "B734": 753, "B735": 124, "F5": 81, "IL76": 54, "L410": 129, "MD82": 84, "MD83": 101, "MD87": 9, "P3": 65, "YK42": 22, "T204": 92, "T154": 21, "SHIP": 45, "BTB2": 42, "F70": 53, "D328": 251, "B736": 69, "F16": 28, "B742": 71, "DC3": 28, "CORS": 6, "B52": 28, "F100": 12, "U2": 34, "T38": 53, "V22": 33, "AN72": 5, "YK50": 8, "DC6": 3, "MD88": 23, "B779": 13, "L188": 6}}