{"date": "2026-06-21", "total": 5671, "rare": 0, "squawk": 0, "filtered": 908, "types": {"A310": 155, "B732": 34, "B722": 5, "B733": 1262, "B734": 1099, "B735": 483, "DC10": 15, "BALL": 456, "F100": 119, "L410": 198, "MD83": 131, "MD87": 49, "MD88": 73, "P3": 5, "V22": 104, "T204": 216, "SHIP": 210, "BTB2": 161, "MD82": 44, "ZZZZ": 100, "T134": 51, "IL76": 152, "T154": 25, "F70": 132, "DC3": 34, "D328": 29, "AN12": 76, "YK42": 74, "A148": 18, "AN30": 35, "B742": 36, "DC87": 2, "AN26": 29, "L188": 1, "CORS": 17, "AN32": 2, "B736": 19, "A124": 18, "F5": 2}}