{"date": "2026-06-27", "total": 5199, "rare": 0, "squawk": 0, "filtered": 716, "types": {"L188": 34, "A148": 56, "B742": 99, "B733": 868, "B734": 1252, "B735": 296, "DC3": 98, "DC91": 21, "BALL": 407, "F5": 6, "IL76": 233, "L410": 126, "MD83": 163, "MD87": 22, "YK42": 14, "V22": 161, "T204": 166, "SHIP": 179, "BTB2": 117, "D328": 116, "GLF5": 4, "ZZZZ": 123, "B736": 34, "CORS": 3, "F70": 59, "DC6": 2, "F100": 83, "A310": 89, "MD88": 28, "AN32": 70, "T134": 15, "AN12": 19, "A124": 91, "MD82": 20, "AN26": 48, "YK40": 14, "IL62": 8, "T154": 7, "MD11": 16, "P3": 7, "B732": 23, "B722": 2}}