{"date": "2026-06-02", "total": 5800, "rare": 0, "squawk": 12, "filtered": 1018, "types": {"L188": 33, "ZZZZ": 52, "A124": 78, "A310": 92, "B732": 60, "B733": 787, "B734": 1315, "B735": 314, "DC3": 67, "DC10": 52, "F100": 123, "F5": 36, "IL62": 14, "IL76": 137, "L410": 226, "MD81": 1, "MD83": 315, "MD88": 178, "P3": 26, "YK42": 13, "V22": 125, "T204": 202, "SHIP": 124, "BTB2": 332, "F70": 343, "D328": 91, "DC6": 10, "AN32": 255, "B736": 41, "MD82": 22, "B742": 94, "B722": 43, "AN12": 75, "B703": 13, "DC91": 27, "BALL": 31, "AN26": 23, "T134": 8, "YK40": 12, "T154": 10}}