{"date": "2026-06-04", "total": 6646, "rare": 0, "squawk": 1, "filtered": 1229, "types": {"ZZZZ": 69, "A310": 124, "B732": 21, "B722": 48, "B733": 1315, "B734": 1628, "B735": 328, "B736": 56, "DC6": 6, "DC3": 53, "DC10": 26, "DC91": 110, "F100": 143, "F5": 12, "IL76": 222, "MD83": 260, "MD87": 1, "MD88": 101, "P3": 12, "V22": 232, "T204": 68, "BTB2": 376, "F70": 405, "D328": 108, "GLF5": 5, "A124": 41, "A148": 30, "AN12": 78, "MD82": 79, "T154": 23, "L410": 259, "AN32": 139, "IL62": 9, "YK42": 44, "T134": 23, "BALL": 59, "AN26": 43, "F35": 1, "DC87": 12, "B742": 26, "SHIP": 41, "AN72": 6, "YK40": 4}}