{"date": "2026-06-15", "total": 2959, "rare": 0, "squawk": 0, "filtered": 612, "types": {"A310": 30, "B732": 39, "B722": 30, "B733": 573, "B734": 456, "B735": 308, "DC3": 35, "DC10": 38, "DC91": 30, "BALL": 85, "F100": 54, "IL76": 160, "L410": 113, "MD82": 24, "MD87": 110, "MD88": 76, "V22": 18, "T204": 100, "SHIP": 47, "BTB2": 235, "F70": 166, "L188": 17, "ZZZZ": 5, "MD81": 5, "B736": 13, "P3": 3, "MD83": 43, "AN12": 31, "YK42": 23, "T154": 2, "B742": 39, "B1": 7, "YK40": 2, "A124": 20, "T134": 3, "D328": 12, "AN26": 3, "A148": 3, "A3ST": 1}}