{"date": "2026-06-15", "total": 13364, "rare": 50, "squawk": 0, "filtered": 2003, "types": {"A310": 202, "B732": 363, "B722": 86, "B733": 2257, "B734": 2696, "B735": 927, "DC3": 241, "DC10": 91, "DC91": 33, "BALL": 466, "F100": 169, "IL76": 542, "L410": 567, "MD82": 190, "MD87": 187, "MD88": 160, "V22": 145, "T204": 318, "SHIP": 334, "BTB2": 552, "F70": 426, "L188": 39, "ZZZZ": 288, "MD81": 32, "B736": 169, "P3": 71, "MD83": 347, "AN12": 105, "YK42": 41, "T154": 58, "B742": 225, "B1": 18, "YK40": 23, "A124": 50, "T134": 29, "D328": 303, "AN26": 74, "A148": 53, "A3ST": 21, "AN32": 8, "B52": 9, "AN72": 2, "IL62": 1, "F15": 10, "F5": 190, "KFIR": 3, "CORS": 9, "E6": 56, "F16": 62, "WB57": 50, "B779": 36, "DC6": 13, "GLF3": 11, "T34T": 6}}