{"date": "2026-04-15", "total": 9016, "rare": 0, "squawk": 0, "filtered": 1477, "types": {"ZZZZ": 85, "A124": 65, "A310": 64, "AN26": 102, "B74S": 21, "B742": 151, "B732": 110, "B722": 29, "B733": 1202, "B734": 2584, "B735": 446, "B736": 181, "DC3": 139, "BALL": 193, "F100": 157, "F5": 57, "L410": 463, "MD83": 106, "MD87": 18, "MD88": 130, "V22": 421, "F70": 425, "P3": 76, "T204": 189, "SHIP": 121, "D328": 202, "DC6": 9, "MD82": 81, "AN72": 27, "IL76": 484, "AN32": 171, "YK42": 39, "L188": 36, "A148": 73, "BER2": 33, "T154": 14, "BTB2": 49, "CORS": 17, "AN12": 110, "A3ST": 28, "T38": 45, "MD81": 13, "IL62": 13, "KFIR": 9, "T134": 9, "YK40": 2, "WHK2": 5, "B52": 5, "U2": 3, "T34T": 2, "DC10": 1, "MD11": 1}}