{"date": "2026-04-17", "total": 11590, "rare": 29, "squawk": 0, "filtered": 1816, "types": {"ZZZZ": 359, "A124": 158, "A310": 196, "AN32": 211, "B742": 218, "B732": 247, "B703": 35, "B733": 1922, "B734": 2777, "B735": 463, "B736": 258, "DC6": 44, "DC3": 136, "BALL": 461, "F100": 90, "F5": 208, "IL76": 421, "MD82": 112, "MD83": 148, "P3": 77, "V22": 514, "T204": 254, "SHIP": 299, "BTB2": 144, "F70": 285, "D328": 294, "WB57": 29, "T38": 57, "MD87": 17, "L188": 8, "B722": 27, "F28": 2, "L410": 534, "IL62": 51, "YK42": 95, "MD88": 60, "T154": 89, "AN12": 20, "AN26": 117, "A148": 11, "CORS": 5, "AN72": 6, "T134": 1, "F104": 9, "U2": 33, "YK50": 3, "KFIR": 7, "GLF3": 41, "DC10": 10, "F16": 9, "B779": 14, "MD81": 4}}