{"date": "2026-06-02", "total": 10482, "rare": 4, "squawk": 12, "filtered": 1570, "types": {"L188": 33, "ZZZZ": 185, "A124": 207, "A310": 178, "B732": 220, "B733": 1387, "B734": 2624, "B735": 654, "DC3": 151, "DC10": 52, "F100": 154, "F5": 88, "IL62": 14, "IL76": 292, "L410": 422, "MD81": 21, "MD83": 484, "MD88": 193, "P3": 72, "YK42": 13, "V22": 136, "T204": 368, "SHIP": 188, "BTB2": 462, "F70": 424, "D328": 158, "DC6": 10, "AN32": 332, "B736": 137, "MD82": 76, "B742": 115, "B722": 54, "AN12": 162, "B703": 13, "DC91": 49, "BALL": 81, "AN26": 66, "T134": 22, "YK40": 14, "T154": 63, "AN72": 7, "B741": 6, "MD11": 6, "KFIR": 10, "MD87": 19, "GLF3": 23, "A148": 3, "B52": 16, "F16": 12, "WB57": 4, "U2": 2}}