{"date": "2026-06-08", "total": 3329, "rare": 0, "squawk": 0, "filtered": 723, "types": {"AN32": 107, "B733": 483, "B734": 559, "B735": 222, "DC3": 22, "DC10": 6, "IL76": 176, "L410": 194, "MD81": 14, "MD87": 25, "MD88": 30, "V22": 107, "T204": 107, "T134": 7, "SHIP": 84, "BTB2": 296, "F70": 257, "D328": 51, "AN26": 41, "B722": 76, "B736": 9, "MD83": 65, "T38": 10, "F100": 55, "MD82": 25, "AN12": 78, "ZZZZ": 2, "T154": 42, "BALL": 72, "B742": 20, "AN30": 27, "YK42": 11, "DC6": 19, "A148": 14, "A124": 11, "AN72": 5}}