{"date": "2026-06-08", "total": 9012, "rare": 2, "squawk": 0, "filtered": 1813, "types": {"AN32": 172, "B733": 1286, "B734": 1797, "B735": 493, "DC3": 97, "DC10": 23, "IL76": 430, "L410": 544, "MD81": 18, "MD87": 37, "MD88": 30, "V22": 234, "T204": 343, "T134": 14, "SHIP": 250, "BTB2": 409, "F70": 387, "D328": 292, "AN26": 92, "B722": 136, "B736": 86, "MD83": 250, "T38": 25, "F100": 77, "MD82": 134, "AN12": 155, "ZZZZ": 158, "T154": 90, "BALL": 73, "B742": 74, "AN30": 41, "YK42": 38, "DC6": 26, "A148": 62, "A124": 44, "AN72": 12, "IL62": 3, "YK40": 6, "DC87": 28, "P3": 98, "B732": 156, "F5": 129, "GLF3": 24, "B703": 25, "KFIR": 6, "B52": 59, "F16": 18, "A310": 19, "F15": 4, "B1": 4, "WB57": 2, "GLF5": 2}}