{"date": "2026-04-27", "total": 11603, "rare": 1, "squawk": 0, "filtered": 1699, "types": {"ZZZZ": 311, "A124": 231, "B732": 283, "B733": 1998, "B734": 1979, "B735": 599, "B736": 169, "DC3": 147, "BALL": 142, "F100": 178, "IL76": 426, "L410": 578, "MD82": 89, "MD87": 50, "MD88": 104, "P3": 52, "YK42": 44, "V22": 274, "T204": 637, "SHIP": 387, "BTB2": 301, "E6": 59, "F70": 385, "MD81": 31, "AN32": 210, "L188": 6, "B722": 100, "MD83": 212, "F35": 2, "IL62": 66, "AN12": 129, "BER2": 1, "A310": 218, "T154": 62, "A148": 41, "T134": 19, "D328": 381, "AN30": 8, "AN26": 41, "YK50": 3, "B742": 98, "YK40": 7, "U2": 72, "F5": 234, "B52": 70, "F16": 60, "B779": 27, "T34T": 4, "T38": 37, "WB57": 1, "DC6": 33, "B703": 7}}