{"date": "2026-04-16", "total": 5946, "rare": 0, "squawk": 0, "filtered": 1108, "types": {"L188": 11, "ZZZZ": 47, "A124": 179, "B742": 124, "B732": 37, "B722": 42, "B733": 1123, "B734": 1369, "B735": 148, "B736": 89, "DC6": 1, "BALL": 114, "F100": 113, "L410": 394, "MD83": 70, "MD87": 9, "MD88": 128, "V22": 368, "T204": 109, "SHIP": 57, "BTB2": 121, "F70": 382, "D328": 116, "DC3": 12, "IL76": 263, "MD82": 13, "AN12": 27, "AN32": 160, "B703": 16, "AN72": 33, "IL62": 26, "DC91": 30, "P3": 14, "T134": 14, "T154": 13, "A148": 35, "AN26": 51, "A310": 28, "YK42": 24, "YK40": 12, "A3ST": 18, "DC87": 5, "EC35": 1}}