{"date": "2026-04-23", "total": 8827, "rare": 0, "squawk": 0, "filtered": 1463, "types": {"ZZZZ": 191, "A124": 147, "A310": 139, "B703": 34, "B733": 1354, "B734": 2209, "B735": 427, "B736": 146, "DC6": 8, "DC3": 101, "BALL": 307, "F100": 158, "IL76": 311, "L410": 400, "MD82": 80, "MD83": 187, "MD87": 45, "MD88": 55, "P3": 19, "V22": 281, "T204": 206, "SHIP": 280, "F70": 426, "D328": 179, "B732": 128, "F16": 37, "F35": 8, "T38": 23, "L188": 12, "AN32": 209, "AN12": 128, "B742": 88, "GLF3": 7, "IL62": 70, "B722": 50, "AN30": 28, "T134": 24, "YK42": 21, "BTB2": 11, "AN26": 123, "F27": 3, "A148": 40, "DC87": 23, "A3ST": 9, "BER2": 31, "DC91": 18, "F15": 11, "AN72": 5, "F5": 22, "YK50": 4, "E6": 4}}