{"date": "2026-06-02", "total": 14385, "rare": 42, "squawk": 12, "filtered": 1985, "types": {"L188": 33, "ZZZZ": 272, "A124": 253, "A310": 215, "B732": 412, "B733": 1999, "B734": 3626, "B735": 816, "DC3": 300, "DC10": 77, "F100": 173, "F5": 247, "IL62": 26, "IL76": 375, "L410": 490, "MD81": 34, "MD83": 632, "MD88": 256, "P3": 112, "YK42": 13, "V22": 303, "T204": 440, "SHIP": 233, "BTB2": 514, "F70": 476, "D328": 212, "DC6": 24, "AN32": 349, "B736": 180, "MD82": 118, "B742": 115, "B722": 56, "AN12": 166, "B703": 33, "DC91": 62, "BALL": 117, "AN26": 116, "T134": 23, "YK40": 14, "T154": 85, "AN72": 7, "B741": 6, "MD11": 6, "KFIR": 10, "MD87": 53, "GLF3": 49, "A148": 19, "B52": 44, "F16": 52, "WB57": 42, "U2": 40, "B1": 11, "E6": 16, "GLF5": 7, "B779": 24, "RFAL": 2}}