{"date": "2026-06-23", "total": 14329, "rare": 40, "squawk": 0, "filtered": 1844, "types": {"L188": 8, "A310": 184, "AN32": 44, "B732": 312, "B733": 2758, "B734": 3543, "B735": 1078, "B736": 120, "DC3": 332, "BALL": 621, "F100": 165, "L410": 474, "MD83": 333, "MD87": 184, "MD88": 232, "V22": 268, "U2": 16, "T204": 350, "SHIP": 322, "BTB2": 198, "F70": 529, "D328": 335, "DC10": 60, "ZZZZ": 188, "IL76": 371, "MD82": 116, "DC6": 12, "AN12": 70, "A148": 54, "P3": 95, "IL62": 28, "AN26": 59, "B742": 132, "YK42": 21, "F35": 6, "A124": 93, "A3ST": 6, "B722": 52, "YK40": 1, "T154": 49, "MD81": 5, "MD11": 63, "F5": 91, "GLF5": 31, "F16": 72, "EC35": 14, "T38": 38, "KFIR": 12, "BE20": 21, "T134": 5, "WB57": 40, "L101": 29, "YK50": 3, "B52": 48, "GLF3": 23, "B779": 15}}