{"date": "2026-06-11", "total": 7387, "rare": 0, "squawk": 0, "filtered": 1247, "types": {"ZZZZ": 80, "A310": 63, "AN12": 126, "B732": 60, "B733": 1154, "B734": 2018, "B735": 293, "B736": 70, "DC10": 73, "BALL": 25, "F100": 160, "F5": 7, "IL76": 268, "L410": 268, "MD82": 79, "MD83": 253, "MD87": 40, "P3": 16, "V22": 247, "T204": 329, "SHIP": 89, "BTB2": 342, "F70": 386, "KFIR": 6, "T38": 8, "YK42": 29, "DC6": 3, "D328": 140, "DC91": 46, "B722": 67, "B742": 67, "MD88": 135, "AN32": 135, "F35": 2, "T154": 40, "AN30": 37, "AN26": 47, "DC3": 61, "A124": 19, "T134": 20, "YK40": 19, "AN72": 2, "A148": 22, "IL62": 6, "DC87": 13, "B52": 12, "MD81": 5}}