{"date": "2026-06-29", "total": 3157, "rare": 0, "squawk": 0, "filtered": 564, "types": {"A124": 35, "A310": 76, "AN12": 53, "AN32": 102, "B742": 16, "B722": 48, "B733": 693, "B734": 434, "B735": 272, "DC91": 3, "BALL": 223, "F100": 78, "F5": 1, "IL76": 155, "L410": 140, "MD11": 1, "MD83": 56, "MD87": 28, "YK42": 17, "V22": 35, "T204": 137, "SHIP": 56, "BTB2": 92, "F70": 135, "ZZZZ": 17, "MD82": 17, "T38": 2, "AN26": 61, "DC10": 15, "A148": 27, "F27": 4, "P3": 4, "L188": 3, "B732": 22, "DC3": 4, "D328": 41, "YK40": 25, "MD88": 8, "B1": 1, "B736": 9, "T154": 5, "F16": 6}}