{"date": "2026-06-03", "total": 10385, "rare": 0, "squawk": 0, "filtered": 1684, "types": {"A310": 162, "AN12": 200, "B732": 183, "B733": 1494, "B734": 2734, "B735": 732, "B736": 141, "DC6": 9, "DC3": 136, "F100": 200, "F5": 62, "IL76": 262, "MD82": 142, "MD83": 340, "MD87": 42, "MD88": 143, "V22": 441, "T204": 387, "SHIP": 124, "BTB2": 296, "F70": 403, "D328": 200, "AN26": 123, "DC10": 72, "T154": 50, "A148": 59, "DC91": 30, "BALL": 45, "ZZZZ": 166, "L410": 412, "T134": 28, "AN32": 167, "YK42": 22, "AN30": 32, "B742": 146, "P3": 32, "BER2": 2, "B741": 7, "YK40": 9, "MD81": 19, "F28": 9, "F35": 2, "BE20": 7, "GLF5": 21, "SGUP": 4, "A124": 15, "GLF3": 18, "B1": 2, "F16": 29, "B722": 10, "B52": 9, "T34T": 4, "U2": 1}}