{"date": "2026-05-20", "total": 6037, "rare": 0, "squawk": 0, "filtered": 986, "types": {"A124": 36, "AN12": 6, "B733": 1226, "B734": 1470, "B735": 441, "B736": 92, "DC3": 40, "DC10": 15, "F100": 144, "IL76": 271, "L410": 250, "MD83": 145, "MD87": 84, "MD88": 124, "P3": 15, "V22": 431, "T204": 132, "SHIP": 114, "F70": 278, "D328": 70, "MD82": 48, "BTB2": 25, "T154": 27, "B732": 36, "DC6": 6, "ZZZZ": 28, "BER2": 31, "AN32": 186, "B722": 28, "A148": 57, "B742": 15, "BALL": 13, "A310": 57, "YK42": 8, "AN26": 21, "T134": 7, "IL62": 24, "AN30": 19, "DC91": 9, "A3ST": 8}}