{"date": "2026-05-14", "total": 7345, "rare": 0, "squawk": 0, "filtered": 1262, "types": {"ZZZZ": 42, "B742": 127, "B732": 36, "B703": 19, "B733": 1253, "B734": 1935, "B735": 267, "B736": 127, "DC3": 73, "DC91": 9, "BALL": 113, "F100": 185, "F5": 37, "IL76": 495, "MD83": 288, "MD88": 174, "P3": 14, "V22": 163, "T204": 162, "SHIP": 91, "BTB2": 130, "E6": 39, "F70": 406, "D328": 108, "L410": 242, "MD87": 31, "CORS": 8, "GLF5": 14, "DC6": 2, "MD82": 49, "A310": 54, "AN12": 51, "B74S": 58, "B52": 1, "AN32": 242, "A124": 65, "T134": 13, "YK42": 25, "AN26": 81, "T154": 21, "F35": 1, "A148": 22, "AN72": 10, "B722": 24, "IL62": 21, "BER2": 3, "DC87": 14}}