{"date": "2026-06-23", "total": 16174, "rare": 46, "squawk": 0, "filtered": 1990, "types": {"L188": 25, "A310": 200, "AN32": 49, "B732": 381, "B733": 3113, "B734": 3988, "B735": 1160, "B736": 164, "DC3": 360, "BALL": 643, "F100": 190, "L410": 479, "MD83": 427, "MD87": 208, "MD88": 261, "V22": 299, "U2": 18, "T204": 394, "SHIP": 340, "BTB2": 279, "F70": 588, "D328": 361, "DC10": 86, "ZZZZ": 199, "IL76": 433, "MD82": 148, "DC6": 17, "AN12": 70, "A148": 54, "P3": 95, "IL62": 38, "AN26": 59, "B742": 141, "YK42": 21, "F35": 6, "A124": 108, "A3ST": 6, "B722": 57, "YK40": 1, "T154": 49, "MD81": 5, "MD11": 81, "F5": 118, "GLF5": 31, "F16": 96, "EC35": 14, "T38": 38, "KFIR": 12, "BE20": 21, "T134": 5, "WB57": 46, "L101": 32, "YK50": 3, "B52": 56, "GLF3": 40, "B779": 44, "DC91": 17}}