{"date": "2026-04-11", "total": 6642, "rare": 10, "squawk": 0, "filtered": 1106, "types": {"ZZZZ": 204, "A310": 119, "B779": 38, "B732": 77, "B703": 27, "B733": 1248, "B734": 1386, "B735": 316, "DC3": 53, "BALL": 379, "F100": 112, "IL76": 427, "MD83": 128, "P3": 8, "V22": 101, "T204": 341, "D328": 99, "WB57": 10, "IL62": 75, "F70": 150, "B736": 106, "L410": 334, "SHIP": 71, "GLF3": 8, "A124": 221, "F5": 12, "MD88": 74, "MD82": 24, "F28": 1, "AN12": 94, "E6": 22, "AN32": 155, "GLF5": 6, "B742": 98, "T154": 24, "YK42": 25, "A148": 19, "YK40": 16, "T134": 23, "B722": 6, "MD81": 5}}