{"date": "2026-06-04", "total": 4094, "rare": 0, "squawk": 1, "filtered": 783, "types": {"ZZZZ": 66, "A310": 68, "B732": 8, "B722": 31, "B733": 782, "B734": 1051, "B735": 157, "B736": 46, "DC6": 6, "DC3": 46, "DC10": 26, "DC91": 100, "F100": 85, "F5": 12, "IL76": 135, "MD83": 169, "MD87": 1, "MD88": 72, "P3": 6, "V22": 193, "T204": 30, "BTB2": 204, "F70": 280, "D328": 65, "GLF5": 5, "A124": 41, "A148": 19, "AN12": 44, "MD82": 50, "T154": 18, "L410": 98, "AN32": 72, "IL62": 9, "YK42": 27, "T134": 7, "BALL": 54, "AN26": 7, "F35": 1, "DC87": 2, "B742": 1}}