{"date": "2026-05-27", "total": 7970, "rare": 0, "squawk": 0, "filtered": 1192, "types": {"L188": 6, "A124": 88, "A310": 92, "AN32": 193, "B742": 48, "B732": 34, "B733": 1175, "B734": 2047, "B735": 617, "B736": 149, "DC10": 77, "BALL": 86, "F16": 16, "F100": 170, "IL76": 356, "MD83": 271, "P3": 23, "V22": 187, "T204": 248, "SHIP": 178, "BTB2": 345, "F70": 396, "D328": 105, "MD87": 2, "T154": 32, "E6": 11, "B703": 39, "L410": 314, "MD82": 50, "DC6": 1, "YK42": 43, "AN12": 99, "MD88": 95, "DC3": 38, "F28": 7, "ZZZZ": 88, "T134": 20, "A148": 45, "AN26": 20, "B1": 45, "A3ST": 29, "AN30": 4, "B722": 30, "AN72": 28, "DC87": 18, "MD81": 5}}