{"date": "2026-05-22", "total": 5689, "rare": 0, "squawk": 0, "filtered": 906, "types": {"B742": 106, "B732": 46, "B703": 14, "B733": 859, "B734": 1490, "B735": 387, "B736": 54, "DC6": 13, "DC10": 5, "BALL": 234, "IL76": 405, "MD81": 2, "MD82": 80, "MD83": 241, "MD88": 185, "P3": 21, "V22": 112, "T204": 55, "SHIP": 99, "E6": 21, "D328": 80, "DC3": 51, "MD87": 9, "BTB2": 84, "F70": 234, "ZZZZ": 39, "F5": 19, "F100": 76, "DC91": 47, "L410": 169, "AN26": 29, "T154": 54, "AN32": 156, "A148": 42, "F28": 1, "B741": 7, "YK42": 33, "A310": 22, "AN30": 20, "AN12": 33, "A124": 34, "IL62": 18, "DC87": 3}}