{"date": "2026-05-20", "total": 7054, "rare": 0, "squawk": 0, "filtered": 1162, "types": {"A124": 36, "AN12": 12, "B733": 1384, "B734": 1724, "B735": 533, "B736": 115, "DC3": 63, "DC10": 15, "F100": 162, "IL76": 320, "L410": 304, "MD83": 179, "MD87": 84, "MD88": 128, "P3": 16, "V22": 455, "T204": 140, "SHIP": 140, "F70": 324, "D328": 87, "MD82": 66, "BTB2": 25, "T154": 27, "B732": 40, "DC6": 6, "ZZZZ": 55, "BER2": 31, "AN32": 217, "B722": 28, "A148": 61, "B742": 39, "BALL": 14, "A310": 70, "YK42": 8, "AN26": 32, "T134": 13, "IL62": 35, "AN30": 19, "DC91": 22, "A3ST": 15, "MD81": 6, "F15": 4}}