{"date": "2026-04-27", "total": 2696, "rare": 0, "squawk": 0, "filtered": 512, "types": {"ZZZZ": 45, "A124": 71, "B732": 11, "B733": 533, "B734": 384, "B735": 211, "B736": 12, "DC3": 30, "BALL": 97, "F100": 63, "IL76": 152, "L410": 153, "MD82": 17, "MD87": 11, "MD88": 79, "P3": 25, "YK42": 16, "V22": 48, "T204": 146, "SHIP": 130, "BTB2": 61, "E6": 8, "F70": 114, "MD81": 5, "AN32": 95, "L188": 4, "B722": 32, "MD83": 13, "F35": 2, "IL62": 26, "AN12": 13, "BER2": 1, "A310": 37, "T154": 14, "A148": 12, "T134": 7, "D328": 16, "AN30": 2}}