{"date": "2026-04-17", "total": 3840, "rare": 12, "squawk": 0, "filtered": 756, "types": {"ZZZZ": 23, "A124": 28, "A310": 34, "AN32": 76, "B742": 72, "B732": 64, "B703": 35, "B733": 649, "B734": 1136, "B735": 149, "B736": 73, "DC6": 13, "DC3": 25, "BALL": 133, "F100": 54, "F5": 15, "IL76": 102, "MD82": 10, "MD83": 52, "P3": 15, "V22": 337, "T204": 86, "SHIP": 94, "BTB2": 65, "F70": 132, "D328": 48, "WB57": 12, "T38": 9, "MD87": 6, "L188": 8, "B722": 7, "F28": 2, "L410": 150, "IL62": 25, "YK42": 17, "MD88": 52, "T154": 10, "AN12": 10, "AN26": 12}}