{"date": "2026-05-29", "total": 10539, "rare": 0, "squawk": 0, "filtered": 1611, "types": {"ZZZZ": 232, "AN26": 128, "AN32": 241, "B733": 1766, "B734": 2584, "B735": 631, "B736": 198, "DC3": 234, "DC10": 97, "F16": 20, "F5": 135, "IL76": 390, "MD82": 111, "MD83": 245, "MD87": 29, "V22": 234, "T204": 363, "SHIP": 340, "F70": 313, "D328": 248, "EC35": 36, "L188": 8, "B732": 194, "B742": 129, "IL62": 36, "F100": 92, "L410": 440, "T154": 53, "DC91": 13, "DC6": 11, "MD88": 33, "BALL": 141, "P3": 53, "AN30": 2, "BTB2": 94, "YK42": 43, "A124": 108, "A310": 98, "AN12": 85, "AN72": 61, "A148": 124, "T134": 1, "DC87": 31, "B722": 22, "E6": 25, "B52": 35, "COL3": 6, "GLF3": 14, "L101": 9, "YK50": 3}}