{"date": "2026-05-19", "total": 5902, "rare": 0, "squawk": 0, "filtered": 1105, "types": {"ZZZZ": 45, "A124": 99, "A148": 71, "B742": 146, "B722": 1, "B703": 13, "B733": 859, "B734": 1484, "B735": 303, "F100": 143, "L410": 352, "MD82": 20, "MD87": 38, "MD88": 179, "V22": 142, "T204": 106, "SHIP": 100, "BTB2": 232, "E6": 14, "F70": 358, "D328": 87, "AN32": 193, "B736": 38, "P3": 12, "B52": 14, "MD83": 123, "DC6": 12, "DC3": 33, "MD81": 4, "IL76": 271, "B732": 9, "BALL": 50, "T134": 32, "CORS": 5, "DC91": 39, "YK42": 26, "AN30": 36, "BER2": 14, "AN26": 33, "A310": 109, "YK40": 10, "T154": 10, "A3ST": 16, "AN12": 11, "AN72": 3, "DC87": 7}}