{"date": "2026-05-25", "total": 4287, "rare": 0, "squawk": 0, "filtered": 733, "types": {"ZZZZ": 66, "A124": 58, "B732": 41, "B733": 828, "B734": 668, "B735": 267, "DC10": 17, "BALL": 488, "F100": 121, "IL76": 212, "L410": 161, "MD81": 4, "MD82": 10, "V22": 43, "SHIP": 113, "BTB2": 164, "F70": 251, "AN32": 128, "T204": 136, "DC3": 68, "MD83": 42, "YK42": 28, "B736": 17, "P3": 56, "D328": 14, "MD87": 5, "A310": 68, "B722": 18, "E6": 6, "T134": 11, "AN30": 31, "A148": 34, "AN26": 36, "T154": 23, "AN12": 20, "B742": 27, "YK40": 4, "DC87": 2, "IL62": 1}}