{"date": "2026-06-20", "total": 10566, "rare": 0, "squawk": 1, "filtered": 1382, "types": {"ZZZZ": 296, "B732": 132, "B722": 15, "B733": 1974, "B734": 2518, "B735": 743, "DC3": 200, "BALL": 633, "F100": 184, "IL76": 402, "L410": 453, "MD81": 8, "MD82": 89, "MD83": 313, "MD87": 49, "MD88": 162, "P3": 9, "V22": 228, "T204": 336, "SHIP": 455, "BTB2": 175, "E6": 21, "F70": 133, "D328": 237, "AN12": 102, "IL62": 35, "A310": 188, "DC6": 13, "T134": 12, "F28": 1, "YK42": 12, "AN30": 35, "A148": 36, "AN26": 14, "B736": 52, "B742": 105, "A124": 89, "AN32": 5, "YK40": 23, "B741": 6, "T154": 21, "YK50": 2, "CORS": 1, "EC35": 24, "F5": 4, "B703": 18, "DC10": 2, "L188": 1}}