{"date": "2026-04-29", "total": 4743, "rare": 0, "squawk": 1, "filtered": 900, "types": {"ZZZZ": 44, "A310": 56, "AN12": 10, "B779": 20, "B742": 19, "B732": 2, "B703": 52, "B733": 646, "B734": 1384, "B735": 336, "B736": 46, "DC6": 25, "F16": 9, "F100": 127, "IL76": 201, "MD82": 47, "MD83": 125, "MD87": 20, "MD88": 51, "P3": 23, "V22": 250, "T204": 68, "SHIP": 135, "BTB2": 149, "E6": 22, "F70": 225, "D328": 76, "DC3": 8, "L410": 243, "AN32": 89, "T134": 42, "BALL": 41, "A124": 48, "T154": 21, "AN26": 29, "A148": 25, "AN30": 16, "AN72": 2, "IL62": 11}}