{"date": "2026-04-24", "total": 14533, "rare": 0, "squawk": 0, "filtered": 1890, "types": {"ZZZZ": 256, "A124": 145, "A310": 165, "AN12": 209, "B779": 82, "B732": 305, "B703": 47, "B733": 2344, "B734": 3365, "B735": 577, "B736": 267, "DC6": 41, "BALL": 610, "IL62": 26, "IL76": 538, "L410": 558, "MD83": 344, "MD88": 99, "V22": 317, "T204": 495, "SHIP": 427, "BTB2": 451, "E6": 46, "D328": 417, "MD82": 197, "MD87": 92, "T154": 120, "DC3": 220, "F100": 84, "F16": 56, "T38": 79, "P3": 51, "L188": 26, "YK50": 15, "F70": 367, "F5": 185, "T134": 15, "AN32": 235, "AN26": 93, "BER2": 32, "AN72": 13, "AN30": 57, "A148": 22, "B742": 172, "DC87": 28, "YK42": 60, "B722": 93, "EC35": 16, "U2": 33, "KFIR": 25, "MD81": 9, "F35": 4, "CORS": 3}}