{"date": "2026-04-11", "total": 2273, "rare": 10, "squawk": 0, "filtered": 364, "types": {"ZZZZ": 30, "A310": 24, "B779": 35, "B732": 41, "B703": 27, "B733": 491, "B734": 600, "B735": 106, "DC3": 9, "BALL": 62, "F100": 37, "IL76": 91, "MD83": 56, "P3": 8, "V22": 101, "T204": 66, "D328": 50, "WB57": 10, "IL62": 30, "F70": 50, "B736": 30, "L410": 77, "SHIP": 3, "GLF3": 8, "A124": 69, "F5": 12, "MD88": 36, "MD82": 9, "F28": 1, "AN12": 32, "E6": 12, "AN32": 20, "GLF5": 6, "B742": 12, "T154": 11, "YK42": 11}}