{"date": "2026-06-25", "total": 4748, "rare": 0, "squawk": 2, "filtered": 620, "types": {"L188": 57, "ZZZZ": 32, "B52": 11, "A124": 36, "A148": 18, "A310": 87, "AN32": 72, "B732": 22, "B733": 889, "B734": 1080, "B735": 343, "B736": 57, "DC3": 21, "DC10": 25, "BALL": 159, "F100": 80, "IL76": 101, "L410": 145, "MD11": 3, "MD83": 56, "MD87": 69, "MD88": 75, "YK42": 56, "V22": 328, "U2": 18, "T204": 142, "SHIP": 84, "BTB2": 119, "F70": 234, "D328": 109, "B742": 66, "E6": 18, "L101": 10, "T134": 36, "AN12": 33, "MD82": 7, "F2TH": 2, "T154": 14, "F16": 1, "B722": 15, "AN26": 14, "IL62": 3, "YK40": 1}}