{"date": "2026-05-15", "total": 11411, "rare": 0, "squawk": 0, "filtered": 1549, "types": {"L188": 38, "ZZZZ": 132, "A124": 87, "B742": 157, "B732": 189, "B703": 35, "B733": 1701, "B734": 2784, "B735": 510, "B736": 206, "DC6": 27, "DC3": 123, "BALL": 357, "F100": 139, "IL62": 25, "IL76": 424, "L410": 431, "MD82": 158, "MD83": 525, "MD87": 96, "MD88": 204, "P3": 36, "V22": 360, "T204": 215, "SHIP": 244, "BTB2": 457, "D328": 345, "F70": 310, "YK40": 51, "T38": 53, "AN12": 113, "AN32": 191, "YK42": 34, "T154": 50, "A310": 221, "B722": 29, "AN26": 90, "T134": 14, "B741": 8, "AN72": 10, "F5": 148, "U2": 30, "SR22": 9, "F16": 13, "COL3": 5, "KFIR": 4, "DC10": 10, "MD81": 7, "EC35": 6}}