{"date": "2026-05-31", "total": 8162, "rare": 34, "squawk": 0, "filtered": 1441, "types": {"L188": 33, "A148": 19, "AN12": 74, "B733": 1446, "B734": 1891, "B735": 825, "B736": 37, "DC10": 38, "DC91": 26, "F100": 160, "IL62": 2, "MD83": 126, "MD87": 35, "MD88": 126, "V22": 127, "T204": 356, "SHIP": 176, "BTB2": 339, "E6": 53, "WB57": 34, "ZZZZ": 191, "DC3": 126, "MD82": 111, "L410": 252, "IL76": 421, "F70": 161, "B742": 99, "D328": 127, "AN32": 119, "BALL": 256, "DC6": 3, "B722": 6, "P3": 31, "A124": 7, "A310": 86, "AN26": 33, "T134": 29, "B741": 9, "YK42": 65, "MD81": 16, "B732": 72, "GLF3": 19}}