{"date": "2026-05-12", "total": 4667, "rare": 0, "squawk": 0, "filtered": 980, "types": {"L188": 16, "ZZZZ": 41, "A124": 7, "B779": 2, "B742": 3, "B732": 32, "B722": 39, "B703": 26, "B733": 819, "B734": 1172, "B735": 266, "B736": 31, "DC91": 4, "F16": 13, "F100": 139, "L410": 185, "MD83": 152, "MD88": 183, "P3": 26, "V22": 109, "T204": 91, "SHIP": 78, "BTB2": 191, "E6": 56, "F70": 332, "D328": 55, "IL76": 134, "MD82": 12, "F5": 23, "DC6": 13, "MD87": 12, "AN32": 201, "DC3": 41, "YK40": 8, "IL62": 5, "AN26": 30, "T134": 12, "A148": 10, "T154": 10, "BALL": 9, "AN72": 11, "A310": 42, "B74S": 1, "YK42": 10, "AN30": 6, "AN12": 9}}