{"date": "2026-06-05", "total": 13989, "rare": 3, "squawk": 1, "filtered": 2239, "types": {"ZZZZ": 296, "A124": 113, "A310": 313, "AN32": 201, "B732": 239, "B733": 2456, "B734": 3351, "B735": 854, "B736": 174, "DC6": 24, "DC3": 285, "DC91": 51, "BALL": 241, "MD82": 273, "MD83": 616, "MD88": 141, "P3": 55, "V22": 579, "T204": 295, "D328": 391, "WB57": 3, "GLF3": 52, "IL76": 413, "B742": 144, "F100": 177, "L188": 51, "MD87": 17, "T154": 113, "BTB2": 122, "F70": 290, "L410": 380, "AN12": 121, "A148": 45, "SHIP": 273, "AN26": 110, "B741": 12, "T134": 51, "AN30": 40, "AN72": 30, "B209": 1, "IL62": 24, "YK40": 12, "DC87": 27, "F28": 1, "YK42": 44, "MD11": 27, "EC35": 14, "GLF5": 51, "KFIR": 8, "DC4": 5, "T38": 35, "MD81": 26, "F5": 192, "L101": 34, "F16": 32, "U2": 42, "CORS": 3, "DC10": 19}}