{"date": "2026-05-26", "total": 6512, "rare": 0, "squawk": 0, "filtered": 1144, "types": {"B742": 64, "B732": 84, "B733": 984, "B734": 1523, "B735": 350, "DC3": 99, "DC91": 13, "BALL": 176, "IL62": 51, "IL76": 302, "L410": 367, "MD82": 93, "MD87": 90, "MD88": 179, "T204": 199, "SHIP": 140, "BTB2": 134, "F70": 400, "D328": 14, "P3": 18, "V22": 101, "AN32": 180, "F100": 165, "ZZZZ": 119, "T134": 28, "MD83": 79, "T154": 36, "BER2": 34, "A148": 41, "A310": 111, "A124": 43, "AN12": 81, "AN30": 28, "AN26": 75, "YK42": 9, "YK40": 14, "B736": 62, "AN72": 4, "MD81": 7, "B722": 8, "F16": 6, "E6": 1}}