{"date": "2026-04-19", "total": 4575, "rare": 40, "squawk": 0, "filtered": 1039, "types": {"A124": 93, "A310": 58, "B733": 767, "B734": 877, "B735": 341, "B736": 45, "DC6": 13, "BALL": 292, "F100": 116, "IL76": 137, "MD82": 34, "P3": 16, "V22": 48, "T204": 145, "SHIP": 184, "BTB2": 166, "ZZZZ": 85, "AN72": 35, "E6": 24, "L410": 261, "F70": 120, "DC3": 50, "B742": 89, "MD88": 60, "B732": 24, "D328": 119, "A148": 41, "AN32": 92, "YK42": 38, "B722": 10, "AN30": 5, "EC35": 56, "AN12": 18, "WB57": 40, "MD83": 68, "F5": 5, "T154": 3}}