{"date": "2026-06-16", "total": 13140, "rare": 0, "squawk": 0, "filtered": 1765, "types": {"ZZZZ": 316, "B732": 271, "B733": 2165, "B734": 3224, "B735": 919, "B736": 151, "DC3": 186, "DC10": 97, "DC91": 31, "BALL": 351, "F100": 173, "IL76": 363, "L410": 493, "MD82": 211, "MD83": 384, "MD87": 165, "MD88": 126, "P3": 50, "V22": 545, "T204": 334, "BTB2": 399, "F70": 389, "D328": 193, "SHIP": 315, "DC6": 30, "F28": 2, "AN12": 105, "EC35": 13, "A310": 148, "B742": 127, "AN32": 23, "AN30": 38, "A124": 129, "AN26": 46, "T134": 37, "YK40": 35, "A148": 98, "IL62": 42, "YK42": 66, "AN72": 4, "U2": 55, "DC87": 31, "F35": 3, "T38": 20, "F5": 90, "T154": 45, "B722": 12, "B1": 1, "B741": 5, "YK50": 7, "B779": 27, "MD81": 11, "E6": 12, "F16": 18, "CORS": 4, "L188": 5}}