{"date": "2026-04-08", "total": 13301, "rare": 0, "squawk": 0, "filtered": 2097, "types": {"A124": 136, "A310": 118, "AN32": 246, "B742": 193, "B732": 365, "B722": 56, "B703": 34, "B733": 2317, "B734": 3216, "B735": 645, "B736": 256, "DC6": 40, "DC3": 221, "F100": 178, "F35": 6, "F5": 237, "IL76": 502, "L410": 574, "MD83": 228, "V22": 656, "T204": 333, "SHIP": 132, "BTB2": 152, "F70": 388, "D328": 335, "MD82": 99, "P3": 43, "MD87": 9, "T38": 81, "ZZZZ": 257, "BALL": 373, "F16": 48, "IL62": 62, "MD88": 39, "AN26": 101, "T154": 84, "T134": 38, "YK42": 37, "AN12": 199, "A148": 52, "AN30": 14, "F27": 6, "MD81": 32, "SGUP": 33, "YK50": 6, "DC91": 5, "A3ST": 21, "EC35": 1, "B52": 46, "L188": 4, "CORS": 4, "AN72": 2, "E6": 16, "B779": 16, "GLF5": 5, "GLF3": 4}}