{"date": "2026-06-06", "total": 10460, "rare": 0, "squawk": 0, "filtered": 1631, "types": {"L188": 38, "B52": 24, "A124": 87, "A148": 47, "A310": 237, "B733": 1698, "B734": 2661, "B735": 643, "DC6": 8, "DC3": 236, "F5": 57, "IL76": 459, "MD82": 240, "MD83": 316, "MD87": 75, "V22": 158, "T204": 431, "T154": 44, "SHIP": 357, "BTB2": 304, "F70": 124, "D328": 190, "T134": 37, "B732": 62, "B1": 8, "B736": 71, "F28": 1, "L410": 280, "F100": 154, "ZZZZ": 316, "B742": 155, "AN12": 207, "DC10": 19, "AN32": 112, "BALL": 348, "MD88": 105, "DC91": 1, "YK42": 39, "AN26": 32, "DC87": 29, "YK40": 5, "P3": 17, "MD81": 20, "B741": 3, "CORS": 4, "AN72": 1}}