{"date": "2026-06-20", "total": 10171, "rare": 0, "squawk": 1, "filtered": 1321, "types": {"ZZZZ": 289, "B732": 125, "B722": 15, "B733": 1887, "B734": 2433, "B735": 719, "DC3": 183, "BALL": 604, "F100": 179, "IL76": 386, "L410": 442, "MD81": 8, "MD82": 82, "MD83": 304, "MD87": 44, "MD88": 157, "P3": 9, "V22": 220, "T204": 321, "SHIP": 441, "BTB2": 175, "E6": 21, "F70": 133, "D328": 223, "AN12": 101, "IL62": 35, "A310": 178, "DC6": 13, "T134": 12, "F28": 1, "YK42": 12, "AN30": 35, "A148": 36, "AN26": 14, "B736": 52, "B742": 101, "A124": 84, "AN32": 5, "YK40": 23, "B741": 6, "T154": 16, "YK50": 2, "CORS": 1, "EC35": 24, "F5": 4, "B703": 13, "DC10": 2, "L188": 1}}