{"date": "2026-05-20", "total": 4863, "rare": 0, "squawk": 0, "filtered": 773, "types": {"A124": 36, "AN12": 3, "B733": 981, "B734": 1201, "B735": 330, "B736": 87, "DC3": 33, "DC10": 15, "F100": 122, "IL76": 240, "L410": 168, "MD83": 130, "MD87": 84, "MD88": 108, "P3": 15, "V22": 400, "T204": 96, "SHIP": 82, "F70": 191, "D328": 53, "MD82": 43, "BTB2": 25, "T154": 23, "B732": 36, "DC6": 6, "ZZZZ": 16, "BER2": 15, "AN32": 141, "B722": 28, "A148": 53, "B742": 13, "BALL": 13, "A310": 32, "YK42": 5, "AN26": 15, "T134": 7, "IL62": 10, "AN30": 7}}