{"date": "2026-04-28", "total": 3837, "rare": 0, "squawk": 0, "filtered": 701, "types": {"ZZZZ": 36, "A124": 48, "A310": 42, "B779": 5, "B722": 9, "B703": 45, "B733": 412, "B734": 1066, "B735": 166, "B736": 61, "DC6": 19, "DC91": 39, "F100": 110, "IL76": 79, "L410": 153, "MD83": 50, "MD88": 164, "P3": 12, "V22": 120, "T204": 216, "T154": 47, "SHIP": 85, "BTB2": 123, "F70": 218, "D328": 106, "EC35": 12, "AN12": 36, "B732": 24, "MD81": 5, "MD82": 19, "DC3": 29, "B742": 16, "E6": 27, "AN32": 152, "T38": 9, "F28": 5, "AN26": 28, "BALL": 21, "YK42": 9, "T134": 5, "A3ST": 5, "AN30": 4}}