{"date": "2026-04-17", "total": 9422, "rare": 12, "squawk": 0, "filtered": 1567, "types": {"ZZZZ": 237, "A124": 119, "A310": 133, "AN32": 204, "B742": 186, "B732": 178, "B703": 35, "B733": 1599, "B734": 2386, "B735": 358, "B736": 209, "DC6": 37, "DC3": 91, "BALL": 271, "F100": 83, "F5": 92, "IL76": 377, "MD82": 82, "MD83": 128, "P3": 56, "V22": 457, "T204": 184, "SHIP": 267, "BTB2": 138, "F70": 280, "D328": 210, "WB57": 12, "T38": 38, "MD87": 17, "L188": 8, "B722": 27, "F28": 2, "L410": 492, "IL62": 51, "YK42": 71, "MD88": 52, "T154": 68, "AN12": 20, "AN26": 113, "A148": 11, "CORS": 2, "AN72": 6, "T134": 1, "F104": 4, "U2": 14, "YK50": 3, "KFIR": 6, "GLF3": 6, "DC10": 1}}