{"date": "2026-05-21", "total": 3929, "rare": 9, "squawk": 3, "filtered": 565, "types": {"L188": 17, "B742": 92, "B732": 52, "B703": 27, "B733": 606, "B734": 1071, "B735": 155, "B736": 44, "DC3": 38, "BALL": 91, "F16": 11, "F100": 64, "IL62": 37, "IL76": 167, "L410": 87, "MD82": 22, "MD83": 186, "MD88": 71, "P3": 23, "V22": 329, "T204": 56, "SHIP": 46, "E6": 30, "F70": 209, "D328": 74, "GLF3": 1, "ZZZZ": 6, "A124": 16, "AN32": 65, "DC10": 17, "DC91": 20, "MD87": 3, "BER2": 6, "T134": 12, "BTB2": 54, "F35": 3, "YK42": 19, "A148": 17, "B722": 7, "T154": 29, "A310": 9, "AN12": 8, "AN30": 11, "WB57": 9, "AN26": 6, "B741": 6}}