{"date": "2026-04-17", "total": 1486, "rare": 12, "squawk": 0, "filtered": 280, "types": {"ZZZZ": 6, "A124": 20, "A310": 2, "AN32": 19, "B742": 37, "B732": 30, "B703": 20, "B733": 313, "B734": 447, "B735": 52, "B736": 38, "DC6": 12, "DC3": 13, "BALL": 20, "F100": 15, "F5": 15, "IL76": 28, "MD82": 10, "MD83": 35, "P3": 1, "V22": 169, "T204": 19, "SHIP": 28, "BTB2": 6, "F70": 28, "D328": 22, "WB57": 12, "T38": 9, "MD87": 6, "L188": 8, "B722": 7, "F28": 2, "L410": 17, "IL62": 6, "YK42": 2, "MD88": 12}}