{"date": "2026-05-19", "total": 14491, "rare": 37, "squawk": 0, "filtered": 2028, "types": {"ZZZZ": 169, "A124": 227, "A148": 147, "B742": 260, "B722": 18, "B703": 14, "B733": 2155, "B734": 3626, "B735": 687, "F100": 204, "L410": 587, "MD82": 122, "MD87": 166, "MD88": 246, "V22": 688, "T204": 302, "SHIP": 228, "BTB2": 348, "E6": 14, "F70": 503, "D328": 275, "AN32": 238, "B736": 260, "P3": 73, "B52": 45, "MD83": 344, "DC6": 53, "DC3": 212, "MD81": 26, "IL76": 544, "B732": 278, "BALL": 71, "T134": 49, "CORS": 5, "DC91": 64, "YK42": 48, "AN30": 64, "BER2": 14, "AN26": 50, "A310": 232, "YK40": 10, "T154": 43, "A3ST": 31, "AN12": 105, "AN72": 3, "DC87": 33, "B741": 2, "F5": 353, "EC35": 16, "L188": 23, "B779": 5, "B1": 9, "GLF3": 34, "WB57": 37, "U2": 42, "T2": 22, "F16": 53, "F28": 2, "DC4": 12}}