{"date": "2026-06-01", "total": 2205, "rare": 0, "squawk": 0, "filtered": 444, "types": {"A124": 21, "AN12": 35, "B732": 23, "B733": 363, "B734": 387, "B735": 145, "B736": 24, "DC3": 35, "DC91": 48, "IL76": 151, "L410": 80, "MD82": 13, "MD83": 38, "V22": 127, "T204": 43, "T134": 3, "SHIP": 43, "BTB2": 136, "F70": 149, "DC10": 5, "P3": 23, "F100": 78, "MD88": 52, "MD81": 4, "ZZZZ": 4, "B722": 17, "T154": 1, "AN32": 91, "BER2": 21, "A148": 16, "B742": 15, "BALL": 2, "L188": 1, "AN26": 4, "AN30": 4, "A310": 2, "D328": 1}}